[
  {
      "model": "tasks.timelog",
      "pk": 1,
      "fields": {
          "task": 1,
          "start_time": "2024-10-09T14:00:00Z",
          "duration": "00:15:00"
      }
  },
  {
      "model": "tasks.timelog",
      "pk": 2,
      "fields": {
          "task": 2,
          "start_time": "2024-10-10T10:30:00Z"
      }
  },
  {
      "model": "tasks.timelog",
      "pk": 3,
      "fields": {
          "task": 3,
          "start_time": "2024-10-11T09:00:00Z",
          "duration": "00:15:00"
      }
  },
  {
      "model": "tasks.timelog",
      "pk": 4,
      "fields": {
          "task": 3,
          "start_time": "2024-10-11T09:15:00Z",
          "duration": "00:30:00"
      }
  },
  {
      "model": "tasks.timelog",
      "pk": 5,
      "fields": {
          "task": 4,
          "start_time": "2024-10-11T13:00:00Z",
          "duration": "00:45:00"
      }
  },
  {
      "model": "tasks.timelog",
      "pk": 6,
      "fields": {
          "task": 4,
          "start_time": "2024-10-11T14:00:00Z",
          "duration": "00:45:00"
      }
  }
]
